{
  "markdown": {
    "id": "7277b5d5-bcbc-4024-9496-cff7b4b64322",
    "markdown": "Good design isn't just about aesthetics—it's about creating interfaces that are intuitive, accessible, and delightful to use. Here are the core principles that guide my approach to web interface design.\n## Clarity Over Cleverness\nThe primary goal of any interface is to communicate clearly. Users should never have to guess what an element does or where they should click next.\n**Key practices:**\n- Use descriptive labels instead of clever metaphors\n- Maintain consistent terminology throughout the interface\n- Provide clear visual hierarchy with typography and spacing\n- Show system status and provide feedback for user actions\n## Progressive Disclosure\nDon't overwhelm users with every option at once. Reveal complexity gradually as users need it.\n> *Good interfaces work like a conversation—they reveal information at the right pace, neither too much nor too little.*\n**Implementation approaches:**\n- Start with the most common use cases\n- Use expandable sections for advanced options\n- Provide defaults that work for most users\n- Allow power users to access advanced features without forcing them on everyone\n## Accessibility First\nAccessible design isn't a feature—it's a fundamental requirement. When you design for accessibility, everyone benefits.\n**Essential considerations:**\n- Ensure sufficient color contrast (WCAG 2.1 Level AA minimum)\n- Support keyboard navigation for all interactive elements\n- Provide meaningful alt text for images\n- Test with screen readers\n- Design for various input methods (touch, mouse, keyboard)\n## Performance as Design\nFast interfaces feel more responsive and trustworthy. Performance is a design feature, not just an engineering concern.\n**Design for performance:**\n- Optimize images and assets\n- Show loading states for operations that take time\n- Use skeleton screens instead of spinners when possible\n- Prioritize above-the-fold content\n- Consider the perceived performance, not just actual metrics\n## Consistency Breeds Familiarity\nConsistent interfaces require less cognitive load. Users can transfer knowledge from one part of your application to another.\n**Build consistency through:**\n- Design systems and component libraries\n- Shared interaction patterns\n- Uniform spacing and layout grids\n- Consistent microcopy and tone of voice\n## Design for Error\nUsers will make mistakes. Great interfaces anticipate errors and help users recover gracefully.\n**Error-prevention strategies:**\n- Provide clear constraints and validation\n- Confirm destructive actions\n- Make it easy to undo actions\n- Write helpful error messages that explain the problem and suggest solutions\n## Mobile-First Thinking\nStarting with mobile constraints forces you to prioritize what truly matters.\n**Benefits of mobile-first design:**\n- Focuses on core functionality\n- Encourages progressive enhancement\n- Ensures touch-friendly interactive targets\n- Naturally leads to better performance\n---\n**Further reading:**\n- Don Norman's *The Design of Everyday Things*\n- Apple Human Interface Guidelines\n- Material Design principles\n- Nielsen Norman Group articles",
    "object": "page_markdown",
    "truncated": false,
    "unknown_block_ids": []
  },
  "notionApiVersion": "2026-03-11",
  "page": {
    "cover": null,
    "created_by": {
      "id": "ff55607a-3044-4bbb-9667-bc8493a06e9b",
      "object": "user"
    },
    "created_time": "2025-12-21T15:10:00.000Z",
    "icon": null,
    "id": "7277b5d5-bcbc-4024-9496-cff7b4b64322",
    "in_trash": false,
    "is_archived": false,
    "is_locked": false,
    "last_edited_by": {
      "id": "ff55607a-3044-4bbb-9667-bc8493a06e9b",
      "object": "user"
    },
    "last_edited_time": "2026-01-12T17:25:00.000Z",
    "object": "page",
    "parent": {
      "data_source_id": "2d0fe8dd-acd6-81fb-8702-000b039af795",
      "database_id": "2d0fe8dd-acd6-81ff-bfc5-f9bbd873cc36",
      "type": "data_source_id"
    },
    "properties": {
      "Date": {
        "date": {
          "end": null,
          "start": "2024-12-01",
          "time_zone": null
        },
        "id": "dp_o",
        "type": "date"
      },
      "Description": {
        "id": "10243cf2-965e-450d-99ee-dc6076017363",
        "rich_text": [
          {
            "annotations": {
              "bold": false,
              "code": false,
              "color": "default",
              "italic": false,
              "strikethrough": false,
              "underline": false
            },
            "href": null,
            "plain_text": "Core principles for creating intuitive and accessible web interfaces.",
            "text": {
              "content": "Core principles for creating intuitive and accessible web interfaces.",
              "link": null
            },
            "type": "text"
          }
        ],
        "type": "rich_text"
      },
      "NavigationOrder": {
        "id": "~%3EIP",
        "number": null,
        "type": "number"
      },
      "ShowInNavigation": {
        "checkbox": false,
        "id": "eCNL",
        "type": "checkbox"
      },
      "Slug": {
        "id": "A%3Cgx",
        "rich_text": [
          {
            "annotations": {
              "bold": false,
              "code": false,
              "color": "default",
              "italic": false,
              "strikethrough": false,
              "underline": false
            },
            "href": null,
            "plain_text": "design-principles",
            "text": {
              "content": "design-principles",
              "link": null
            },
            "type": "text"
          }
        ],
        "type": "rich_text"
      },
      "Status": {
        "id": "ece115aa-d10f-4ea0-83b3-ea2a43e6e71e",
        "select": {
          "color": "green",
          "id": "7abc61d4-b405-480d-b699-12588755fa65",
          "name": "Published"
        },
        "type": "select"
      },
      "Tags": {
        "id": "0d131b96-a11a-4078-85a2-06eef84c7be6",
        "multi_select": [
          {
            "color": "default",
            "id": "a3d8eb51-77ce-4e83-a9ae-68da9cee63fa",
            "name": "Design"
          },
          {
            "color": "pink",
            "id": "2382b30f-9881-4a8b-ae7f-2d34979c4fb9",
            "name": "Website"
          },
          {
            "color": "blue",
            "id": "8ee26c03-c874-4114-a2dd-e10cc9ea46dd",
            "name": "Frontend"
          }
        ],
        "type": "multi_select"
      },
      "Title": {
        "id": "title",
        "title": [
          {
            "annotations": {
              "bold": false,
              "code": false,
              "color": "default",
              "italic": false,
              "strikethrough": false,
              "underline": false
            },
            "href": null,
            "plain_text": "Design Principles for Web Interfaces",
            "text": {
              "content": "Design Principles for Web Interfaces",
              "link": null
            },
            "type": "text"
          }
        ],
        "type": "title"
      },
      "Type": {
        "id": "c832da20-339d-4a80-9a7b-62f98d5a8996",
        "select": {
          "color": "blue",
          "id": "5aff2f95-fd1e-489b-8840-bf10bc9519cb",
          "name": "Post"
        },
        "type": "select"
      }
    },
    "public_url": "https://hyf0.notion.site/Design-Principles-for-Web-Interfaces-7277b5d5bcbc40249496cff7b4b64322",
    "url": "https://app.notion.com/p/Design-Principles-for-Web-Interfaces-7277b5d5bcbc40249496cff7b4b64322"
  },
  "schemaVersion": 1,
  "unknownBlocks": []
}
